{"id":"792A8890-5125-477F-B67C-2C3CF5C6036A","__createdAt":"2016-01-08T12:12:23.580Z","__updatedAt":"2016-02-23T19:25:32.144Z","__version":{"0":0,"1":0,"2":0,"3":0,"4":0,"5":15,"6":137,"7":20,"length":8},"__deleted":false,"match_venue":"Dubai Cricket Stadium","match_time":"21:00","match_teamA":"2C6999C9-8A5C-4A19-B37F-BAB963EA2CE0|Quetta Gladiators|1453111043838-team.png","match_teamB":"6CAF4B50-0209-4639-951D-C67E624CC64A|Islamabad United|1453111086101-team.png","match_image":"","match_visibility":null,"match_teamA_id":"2C6999C9-8A5C-4A19-B37F-BAB963EA2CE0","match_teamA_name":"Quetta Gladiators","match_teamB_id":"6CAF4B50-0209-4639-951D-C67E624CC64A","match_teamB_name":"Islamabad United","match_date":"02/23/2016","scoreboard":"{\"matchEnd\":\"Islamabad United Won by 6 wickets\",\"toss\":{\"wonBy\":\"TeamB\",\"wonAction\":{\"Batting\":false,\"Bowling\":true},\"firstInningTeam\":false,\"secondInningTeam\":false},\"firstInning\":{\"batsman\":{\"Ahmad Shehzad\":{\"name\":\"Ahmad Shehzad\",\"onStrick\":false,\"status\":false,\"out\":\"C Samuel Badree B Mohammad Sami\"},\"Bismillah Khan\":{\"name\":\"Bismillah Khan\",\"onStrick\":false,\"status\":false,\"out\":\"C Brad Haddin B Mohammad Irfan\"},\"Kumar Sangakkara\":{\"name\":\"Kumar Sangakkara\",\"onStrick\":false,\"status\":false,\"out\":\"C Imran Khalid B Andre Russell\"},\"Sarfraz Ahmed\":{\"name\":\"Sarfraz Ahmed\",\"onStrick\":false,\"status\":false,\"out\":\"C Dwayne Smith B Mohammad Irfan\"},\"Kevin Pietersen\":{\"name\":\"Kevin Pietersen\",\"onStrick\":false,\"status\":false,\"out\":\"C Asif Ali B Andre Russell\"},\"Grant Elliot\":{\"name\":\"Grant Elliot\",\"onStrick\":false,\"status\":true},\"Mohammad Nawaz\":{\"name\":\"Mohammad Nawaz\",\"onStrick\":false,\"status\":false,\"out\":\"B Samuel Badree\"},\"Nathan McCullum\":{\"name\":\"Nathan McCullum\",\"onStrick\":true,\"status\":true},\"Anwar Ali\":{\"name\":\"Anwar Ali\",\"onStrick\":false,\"status\":false,\"out\":\"C Khalid Latif B Andre Russell\"},\"Zulfiqar Babar\":{\"name\":\"Zulfiqar Babar\"},\"Aizaz Cheema\":{\"name\":\"Aizaz Cheema\"}},\"bowler\":{\"Sharjeel Khan\":{\"name\":\"Sharjeel Khan\",\"bowlerStatus\":false},\"Brad Haddin\":{\"name\":\"Brad Haddin\",\"bowlerStatus\":false},\"Dwayne Smith\":{\"name\":\"Dwayne Smith\",\"bowlerStatus\":false,\"wicket\":0},\"Asif Ali\":{\"name\":\"Asif Ali\",\"bowlerStatus\":false},\"Misbah ul Haq\":{\"name\":\"Misbah ul Haq\",\"bowlerStatus\":false},\"Samuel Badree\":{\"name\":\"Samuel Badree\",\"bowlerStatus\":false,\"wicket\":1},\"Mohammad Irfan\":{\"name\":\"Mohammad Irfan\",\"bowlerStatus\":false,\"wicket\":2},\"Imran Khalid\":{\"name\":\"Imran Khalid\",\"bowlerStatus\":false,\"wicket\":0},\"Mohammad Sami\":{\"name\":\"Mohammad Sami\",\"bowlerStatus\":false,\"wicket\":1},\"Andre Russell\":{\"name\":\"Andre Russell\",\"bowlerStatus\":false,\"wicket\":3},\"Khalid Latif\":{\"name\":\"Khalid Latif\",\"bowlerStatus\":false}},\"bowls\":{\"overs\":[{\"ball\":[{\"score\":0,\"timeStamp\":\"0.934 1456243291\",\"batsman\":\"Bismillah Khan\",\"bowler\":\"Mohammad Irfan\",\"comments\":\"First ball of the match, blocked for no runs\"},{\"score\":0,\"timeStamp\":\"0.342 1456243324\",\"batsman\":\"Bismillah Khan\",\"bowler\":\"Mohammad Irfan\",\"comments\":\"Defended for another dot delivery\"},{\"wicket\":\"catch\",\"outBatsmanByFielder1\":\"Brad Haddin\",\"score\":0,\"timeStamp\":\"0.236 1456243385\",\"batsman\":\"Bismillah Khan\",\"bowler\":\"Mohammad Irfan\",\"comments\":\"OUT! Extra bounce, edged by the batsman and the keeper takes an easy catch behind the stumps\"},{\"score\":0,\"timeStamp\":\"0.198 1456243451\",\"batsman\":\"Kevin Pietersen\",\"bowler\":\"Mohammad Irfan\",\"comments\":\"Angled delivery, the batsman fails to make contact\"},{\"score\":0,\"timeStamp\":\"0.454 1456243493\",\"batsman\":\"Kevin Pietersen\",\"bowler\":\"Mohammad Irfan\",\"comments\":\"Played towards the leg side, but straight to the fielder\"},{\"score\":1,\"timeStamp\":\"0.038 1456243523\",\"batsman\":\"Kevin Pietersen\",\"bowler\":\"Mohammad Irfan\",\"comments\":\"Pushed for a run to end the over\"}]},{\"ball\":[{\"score\":0,\"timeStamp\":\"0.734 1456243601\",\"batsman\":\"Kevin Pietersen\",\"bowler\":\"Imran Khalid\",\"comments\":\"The batsman comes down the track and could only manage to pad it, no runs\"},{\"score\":1,\"timeStamp\":\"0.463 1456243642\",\"batsman\":\"Kevin Pietersen\",\"bowler\":\"Imran Khalid\",\"comments\":\"Played with the straight bat for a run down the ground\"},{\"score\":0,\"timeStamp\":\"0.006 1456243679\",\"batsman\":\"Ahmad Shehzad\",\"bowler\":\"Imran Khalid\",\"comments\":\"Blocked, no runs\"},{\"score\":1,\"timeStamp\":\"0.574 1456243697\",\"batsman\":\"Ahmad Shehzad\",\"bowler\":\"Imran Khalid\",\"comments\":\"The batsman advances down the pitch and takes a run\"},{\"score\":1,\"timeStamp\":\"0.558 1456243727\",\"batsman\":\"Kevin Pietersen\",\"bowler\":\"Imran Khalid\",\"comments\":\"Flicked towards short mid on for a run\"},{\"score\":1,\"timeStamp\":\"0.302 1456243754\",\"batsman\":\"Ahmad Shehzad\",\"bowler\":\"Imran Khalid\",\"comments\":\"Worked towards the leg side for a run to end the over\"}]},{\"ball\":[{\"score\":1,\"timeStamp\":\"0.784 1456243809\",\"batsman\":\"Ahmad Shehzad\",\"bowler\":\"Mohammad Irfan\",\"comments\":\"Extra bounce once again, and a run towards the leg side to start the over\"},{\"boundry\":\"six\",\"score\":\"6\",\"timeStamp\":\"0.007 1456243843\",\"batsman\":\"Kevin Pietersen\",\"bowler\":\"Mohammad Irfan\",\"comments\":\"SIX! Short ball, pulled magnificently towards deep mid wicket for the first maximum of the match\"},{\"score\":0,\"timeStamp\":\"0.584 1456243915\",\"batsman\":\"Kevin Pietersen\",\"bowler\":\"Mohammad Irfan\",\"comments\":\"Driven hard, but straight to the fielder at short cover, no runs\"},{\"score\":0,\"timeStamp\":\"0.142 1456243953\",\"batsman\":\"Kevin Pietersen\",\"bowler\":\"Mohammad Irfan\",\"comments\":\"Shape away from the batsman, dot ball\"},{\"score\":0,\"timeStamp\":\"0.662 1456243998\",\"batsman\":\"Kevin Pietersen\",\"bowler\":\"Mohammad Irfan\",\"comments\":\"Hit hard towards the bowler, no runs\"},{\"score\":2,\"timeStamp\":\"0.774 1456244047\",\"batsman\":\"Kevin Pietersen\",\"bowler\":\"Mohammad Irfan\",\"comments\":\"Pulled away towards mid wicket for a couple of runs to end the over\"}]},{\"ball\":[{\"score\":0,\"timeStamp\":\"0.758 1456244114\",\"batsman\":\"Ahmad Shehzad\",\"bowler\":\"Samuel Badree\",\"comments\":\"Googly to start the spell, dot ball\"},{\"boundry\":\"four\",\"score\":\"4\",\"timeStamp\":\"0.597 1456244134\",\"batsman\":\"Ahmad Shehzad\",\"bowler\":\"Samuel Badree\",\"comments\":\"FOUR! The batsman comes down the track, and hits it past mid off for a boundary\"},{\"score\":2,\"timeStamp\":\"0.726 1456244177\",\"batsman\":\"Ahmad Shehzad\",\"bowler\":\"Samuel Badree\",\"comments\":\"A quick couple of runs towards the leg side\"},{\"score\":1,\"timeStamp\":\"0.246 1456244223\",\"batsman\":\"Ahmad Shehzad\",\"bowler\":\"Samuel Badree\",\"comments\":\"A single towards the off side, excellent fielding to stop more runs\"},{\"score\":1,\"timeStamp\":\"0.67 1456244248\",\"batsman\":\"Kevin Pietersen\",\"bowler\":\"Samuel Badree\",\"comments\":\"A single towards the leg side\"},{\"boundry\":\"four\",\"score\":\"4\",\"timeStamp\":\"0.926 1456244271\",\"batsman\":\"Ahmad Shehzad\",\"bowler\":\"Samuel Badree\",\"comments\":\"FOUR! Hit straight down the ground for another boundary to end the over\"}]},{\"ball\":[{\"score\":0,\"timeStamp\":\"0.138 1456244385\",\"batsman\":\"Kevin Pietersen\",\"bowler\":\"Mohammad Sami\",\"comments\":\"Hit towards the fielder, no runs\"},{\"score\":1,\"timeStamp\":\"0.542 1456244403\",\"batsman\":\"Kevin Pietersen\",\"bowler\":\"Mohammad Sami\",\"comments\":\"Worked towards the leg side for a run\"},{\"score\":1,\"timeStamp\":\"0.014 1456244450\",\"batsman\":\"Ahmad Shehzad\",\"bowler\":\"Mohammad Sami\",\"comments\":\"Played towards deep square leg for a run\"},{\"score\":2,\"timeStamp\":\"0.631 1456244492\",\"batsman\":\"Kevin Pietersen\",\"bowler\":\"Mohammad Sami\",\"comments\":\"Hit towards square leg once again, this time for a couple of runs\"},{\"score\":2,\"timeStamp\":\"0.55 1456244532\",\"batsman\":\"Kevin Pietersen\",\"bowler\":\"Mohammad Sami\",\"comments\":\"Pulled over mid on for a double\"},{\"score\":1,\"timeStamp\":\"0.167 1456244578\",\"batsman\":\"Kevin Pietersen\",\"bowler\":\"Mohammad Sami\",\"comments\":\"Driven towards covers for a single to end the over\"}]},{\"ball\":[{\"wicket\":\"catch\",\"outBatsmanByFielder1\":\"Asif Ali\",\"score\":0,\"timeStamp\":\"0.039 1456244708\",\"batsman\":\"Kevin Pietersen\",\"bowler\":\"Andre Russell\",\"comments\":\"OUT! Hit towards the fielder towards the leg side, who takes a stunning catch to get rid of the batsman\"},{\"score\":1,\"timeStamp\":\"0.581 1456244810\",\"batsman\":\"Kumar Sangakkara\",\"bowler\":\"Andre Russell\",\"comments\":\"Defended and a quick single taken to open his account\"},{\"score\":0,\"timeStamp\":\"0.109 1456244836\",\"batsman\":\"Ahmad Shehzad\",\"bowler\":\"Andre Russell\",\"comments\":\"Blocked away for no runs\"},{\"score\":1,\"timeStamp\":\"0.086 1456244867\",\"batsman\":\"Ahmad Shehzad\",\"bowler\":\"Andre Russell\",\"comments\":\"Played towards backward point for another quick run\"},{\"score\":0,\"timeStamp\":\"0.806 1456244898\",\"batsman\":\"Kumar Sangakkara\",\"bowler\":\"Andre Russell\",\"comments\":\"Defended once again, dot ball\"},{\"score\":1,\"timeStamp\":\"0.637 1456244934\",\"batsman\":\"Kumar Sangakkara\",\"bowler\":\"Andre Russell\",\"comments\":\"Pulled away towards the leg side for a run to end the over\"}]},{\"ball\":[{\"score\":1,\"timeStamp\":\"0.397 1456245024\",\"batsman\":\"Kumar Sangakkara\",\"bowler\":\"Samuel Badree\",\"comments\":\"A run towards short third man to start the new over\"},{\"score\":1,\"timeStamp\":\"0.077 1456245080\",\"batsman\":\"Ahmad Shehzad\",\"bowler\":\"Samuel Badree\",\"comments\":\"Worked towards backward square for just a run\"},{\"score\":1,\"timeStamp\":\"0.541 1456245126\",\"batsman\":\"Kumar Sangakkara\",\"bowler\":\"Samuel Badree\",\"comments\":\"A run towards short mid off to rotate strike\"},{\"score\":1,\"timeStamp\":\"0.198 1456245152\",\"batsman\":\"Ahmad Shehzad\",\"bowler\":\"Samuel Badree\",\"comments\":\"A single taken, tip and run stuff\"},{\"boundry\":\"four\",\"score\":\"4\",\"timeStamp\":\"0.657 1456245173\",\"batsman\":\"Kumar Sangakkara\",\"bowler\":\"Samuel Badree\",\"comments\":\"FOUR! Some poor fielding on display and the batsman benefits a boundary towards third man\"},{\"score\":0,\"timeStamp\":\"0.197 1456245217\",\"batsman\":\"Kumar Sangakkara\",\"bowler\":\"Samuel Badree\",\"comments\":\"A dot ball to end the over\"}]},{\"ball\":[{\"score\":1,\"timeStamp\":\"0.549 1456245298\",\"batsman\":\"Ahmad Shehzad\",\"bowler\":\"Andre Russell\",\"comments\":\"Short ball, played towards the off side for a run\"},{\"score\":0,\"timeStamp\":\"0.468 1456245310\",\"batsman\":\"Kumar Sangakkara\",\"bowler\":\"Andre Russell\",\"comments\":\"Played towards the leg side for a run\"},{\"score\":0,\"timeStamp\":\"0.108 1456245343\",\"batsman\":\"Kumar Sangakkara\",\"bowler\":\"Andre Russell\",\"comments\":\"Hit towards the fielder, dot ball\"},{\"ballPlayedType\":\"LegBye\",\"score\":1,\"timeStamp\":\"0.933 1456245397\",\"batsman\":\"Kumar Sangakkara\",\"bowler\":\"Andre Russell\",\"comments\":\"Bouncer, hit on the helmet for one leg bye\"},{\"score\":1,\"timeStamp\":\"0.469 1456245407\",\"batsman\":\"Ahmad Shehzad\",\"bowler\":\"Andre Russell\",\"comments\":\"Another quick single towards the off side\"},{\"boundry\":\"four\",\"score\":\"4\",\"timeStamp\":\"0.372 1456245441\",\"batsman\":\"Kumar Sangakkara\",\"bowler\":\"Andre Russell\",\"comments\":\"FOUR! Elegantly played towards third man for a boundary to end the over\"}]},{\"ball\":[{\"boundry\":\"four\",\"score\":\"4\",\"timeStamp\":\"0.885 1456245491\",\"batsman\":\"Ahmad Shehzad\",\"bowler\":\"Samuel Badree\",\"comments\":\"FOUR! A lucky outside edge for a boundary towards third man to start the over\"},{\"score\":0,\"timeStamp\":\"0.213 1456245528\",\"batsman\":\"Ahmad Shehzad\",\"bowler\":\"Samuel Badree\",\"comments\":\"Defended, dot ball\"},{\"score\":1,\"timeStamp\":\"0.357 1456245541\",\"batsman\":\"Ahmad Shehzad\",\"bowler\":\"Samuel Badree\",\"comments\":\"Played towards short third man for a run\"},{\"score\":0,\"timeStamp\":\"0.996 1456245564\",\"batsman\":\"Kumar Sangakkara\",\"bowler\":\"Samuel Badree\",\"comments\":\"Played towards the fielder, dot ball\"},{\"score\":0,\"timeStamp\":\"0.495 1456245580\",\"batsman\":\"Kumar Sangakkara\",\"bowler\":\"Samuel Badree\",\"comments\":\"Played towards the fielder, no runs\"},{\"score\":2,\"timeStamp\":\"0.406 1456245619\",\"batsman\":\"Kumar Sangakkara\",\"bowler\":\"Samuel Badree\",\"comments\":\"Played towards the off side and a couple of runs taken\"}]},{\"ball\":[{\"score\":0,\"timeStamp\":\"0.965 1456245690\",\"batsman\":\"Ahmad Shehzad\",\"bowler\":\"Imran Khalid\",\"comments\":\"Defended, no runs\"},{\"score\":0,\"timeStamp\":\"0.565 1456245708\",\"batsman\":\"Ahmad Shehzad\",\"bowler\":\"Imran Khalid\",\"comments\":\"Hit hard towards the bowler, dot delivery\"},{\"score\":1,\"timeStamp\":\"0.901 1456245740\",\"batsman\":\"Ahmad Shehzad\",\"bowler\":\"Imran Khalid\",\"comments\":\"A single taken towards short mid on\"},{\"score\":1,\"timeStamp\":\"0.822 1456245788\",\"batsman\":\"Kumar Sangakkara\",\"bowler\":\"Imran Khalid\",\"comments\":\"Played late towards backward square for a run\"},{\"boundry\":\"four\",\"score\":\"4\",\"timeStamp\":\"0.191 1456245819\",\"batsman\":\"Ahmad Shehzad\",\"bowler\":\"Imran Khalid\",\"comments\":\"FOUR! Poor delivery down the leg side for a boundary\"},{\"boundry\":\"four\",\"score\":\"4\",\"timeStamp\":\"0.604 1456245858\",\"batsman\":\"Ahmad Shehzad\",\"bowler\":\"Imran Khalid\",\"comments\":\"FOUR! Pulled towards square leg for a boundary to end the over\"}]},{\"ball\":[{\"score\":1,\"timeStamp\":\"0.253 1456245992\",\"batsman\":\"Kumar Sangakkara\",\"bowler\":\"Mohammad Irfan\",\"comments\":\"A quick single to start the new over\"},{\"boundry\":\"four\",\"score\":\"4\",\"timeStamp\":\"0.029 1456246033\",\"batsman\":\"Ahmad Shehzad\",\"bowler\":\"Mohammad Irfan\",\"comments\":\"FOUR! Pulled towards deep mid wicket for a boundary\"},{\"score\":0,\"timeStamp\":\"0.38 1456246115\",\"batsman\":\"Ahmad Shehzad\",\"bowler\":\"Mohammad Irfan\",\"comments\":\"Defended, dot ball\"},{\"score\":1,\"timeStamp\":\"0.212 1456246168\",\"batsman\":\"Ahmad Shehzad\",\"bowler\":\"Mohammad Irfan\",\"comments\":\"DROPPED. A chance goes begging and a run is taken\"},{\"score\":0,\"timeStamp\":\"0.1 1456246186\",\"batsman\":\"Kumar Sangakkara\",\"bowler\":\"Mohammad Irfan\",\"comments\":\"Defended, the batsman tries to take a quick single and is sent back\"},{\"boundry\":\"four\",\"score\":\"4\",\"timeStamp\":\"0.06 1456246313\",\"batsman\":\"Kumar Sangakkara\",\"bowler\":\"Mohammad Irfan\",\"comments\":\"FOUR! Inside edge for a lucky boundary to end the over\"}]},{\"ball\":[{\"score\":1,\"timeStamp\":\"0.326 1456246325\",\"batsman\":\"Ahmad Shehzad\",\"bowler\":\"Imran Khalid\",\"comments\":\"Played towards the leg side for a run\"},{\"boundry\":\"four\",\"score\":\"4\",\"timeStamp\":\"0.804 1456246343\",\"batsman\":\"Kumar Sangakkara\",\"bowler\":\"Imran Khalid\",\"comments\":\"FOUR! Played towards deep mid wicket for a boundary\"},{\"score\":1,\"timeStamp\":\"0.725 1456246376\",\"batsman\":\"Kumar Sangakkara\",\"bowler\":\"Imran Khalid\",\"comments\":\"Chipped towards the off side for a run\"},{\"score\":1,\"timeStamp\":\"0.621 1456246407\",\"batsman\":\"Ahmad Shehzad\",\"bowler\":\"Imran Khalid\",\"comments\":\"A run taken to rotate strike\"},{\"boundry\":\"four\",\"score\":\"4\",\"timeStamp\":\"0.984 1456246422\",\"batsman\":\"Kumar Sangakkara\",\"bowler\":\"Imran Khalid\",\"comments\":\"FOUR! Hit like a bullet down the ground for a boundary\"},{\"score\":1,\"timeStamp\":\"0.58 1456246474\",\"batsman\":\"Kumar Sangakkara\",\"bowler\":\"Imran Khalid\",\"comments\":\"Chipped towards long on for a run\"}]},{\"ball\":[{\"boundry\":\"six\",\"score\":\"6\",\"timeStamp\":\"0.701 1456246777\",\"batsman\":\"Kumar Sangakkara\",\"bowler\":\"Mohammad Sami\",\"comments\":\"SIX! Lofted over covers for the maximum, classy shot\"},{\"score\":1,\"timeStamp\":\"0.157 1456246820\",\"batsman\":\"Kumar Sangakkara\",\"bowler\":\"Mohammad Sami\",\"comments\":\"A run towards short fine leg\"},{\"score\":1,\"timeStamp\":\"0.476 1456246866\",\"batsman\":\"Ahmad Shehzad\",\"bowler\":\"Mohammad Sami\",\"comments\":\"A quick run towards the leg side\"},{\"score\":1,\"timeStamp\":\"0.412 1456246901\",\"batsman\":\"Kumar Sangakkara\",\"bowler\":\"Mohammad Sami\",\"comments\":\"Another  quick single\"},{\"score\":2,\"timeStamp\":\"0.02 1456246947\",\"batsman\":\"Ahmad Shehzad\",\"bowler\":\"Mohammad Sami\",\"comments\":\"Flicked towards deep mid wicket for a couple of runs\"},{\"score\":0,\"timeStamp\":\"0.74 1456246988\",\"batsman\":\"Ahmad Shehzad\",\"bowler\":\"Mohammad Sami\",\"comments\":\"Hit towards the bowler, dot ball\"}]},{\"ball\":[{\"boundry\":\"four\",\"score\":\"4\",\"timeStamp\":\"0.553 1456247192\",\"batsman\":\"Kumar Sangakkara\",\"bowler\":\"Dwayne Smith\",\"comments\":\"FOUR! A boundary towards backward square to start the over\"},{\"score\":1,\"timeStamp\":\"0.431 1456247193\",\"batsman\":\"Kumar Sangakkara\",\"bowler\":\"Dwayne Smith\",\"comments\":\"A single to rotate strike\"},{\"score\":1,\"timeStamp\":\"0.415 1456247194\",\"batsman\":\"Ahmad Shehzad\",\"bowler\":\"Dwayne Smith\",\"comments\":\"Another run to keep the scoreboard ticking over\"},{\"boundry\":\"four\",\"score\":\"4\",\"timeStamp\":\"0.639 1456247202\",\"batsman\":\"Kumar Sangakkara\",\"bowler\":\"Dwayne Smith\",\"comments\":\"FOUR! Classy shot towards extra covers for another boundary\"},{\"score\":0,\"timeStamp\":\"0.446 1456247253\",\"batsman\":\"Kumar Sangakkara\",\"bowler\":\"Dwayne Smith\",\"comments\":\"Full and wide, dot ball\"},{\"boundry\":\"six\",\"score\":\"6\",\"timeStamp\":\"0.751 1456247273\",\"batsman\":\"Kumar Sangakkara\",\"bowler\":\"Dwayne Smith\",\"comments\":\"SIX! Short ball, played towards the long off fence for the maximum\"}]},{\"ball\":[{\"score\":1,\"timeStamp\":\"0.894 1456247350\",\"batsman\":\"Ahmad Shehzad\",\"bowler\":\"Andre Russell\",\"comments\":\"Worked towards short third man for a run\"},{\"score\":2,\"timeStamp\":\"0.622 1456247394\",\"batsman\":\"Kumar Sangakkara\",\"bowler\":\"Andre Russell\",\"comments\":\"A couple of runs towards mid on\"},{\"wicket\":\"catch\",\"outBatsmanByFielder1\":\"Imran Khalid\",\"score\":0,\"timeStamp\":\"0.38 1456247445\",\"batsman\":\"Kumar Sangakkara\",\"bowler\":\"Andre Russell\",\"comments\":\"OUT! Slow ball, hit straight towards the fielder at long on\"},{\"score\":1,\"timeStamp\":\"0.627 1456247559\",\"batsman\":\"Mohammad Nawaz\",\"bowler\":\"Andre Russell\",\"comments\":\"Top edged for a run, almost a confusion between the batsmen\"},{\"boundry\":\"four\",\"score\":\"4\",\"timeStamp\":\"0.683 1456247591\",\"batsman\":\"Ahmad Shehzad\",\"bowler\":\"Andre Russell\",\"comments\":\"FOUR! Flicked towards the leg side for a boundary\"},{\"boundry\":\"four\",\"score\":\"4\",\"timeStamp\":\"0.854 1456247656\",\"batsman\":\"Ahmad Shehzad\",\"bowler\":\"Andre Russell\",\"comments\":\"FOUR! Yorker, worked away beautifully towards backward square for another boundary to end the over\"}]},{\"ball\":[{\"score\":0,\"timeStamp\":\"0.923 1456247743\",\"batsman\":\"Mohammad Nawaz\",\"bowler\":\"Samuel Badree\",\"comments\":\"A googly, the batsman fails to pick\"},{\"score\":0,\"timeStamp\":\"0.874 1456247760\",\"batsman\":\"Mohammad Nawaz\",\"bowler\":\"Samuel Badree\",\"comments\":\"Another dot delivery\"},{\"boundry\":\"six\",\"score\":\"6\",\"timeStamp\":\"0.475 1456247779\",\"batsman\":\"Mohammad Nawaz\",\"bowler\":\"Samuel Badree\",\"comments\":\"SIX! Timed perfectly towards long on for a massive biggie\"},{\"wicket\":\"bowled\",\"score\":\"0\",\"timeStamp\":\"0.483 1456247816\",\"batsman\":\"Mohammad Nawaz\",\"bowler\":\"Samuel Badree\",\"comments\":\"OUT! The batsman goes on the back foot and is bowled\"},{\"score\":1,\"timeStamp\":\"0.571 1456247890\",\"batsman\":\"Sarfraz Ahmed\",\"bowler\":\"Samuel Badree\",\"comments\":\"Played towards short third man for a run\"},{\"boundry\":\"four\",\"score\":\"4\",\"timeStamp\":\"0.523 1456247926\",\"batsman\":\"Ahmad Shehzad\",\"bowler\":\"Samuel Badree\",\"comments\":\"FOUR! Cut away for a boundary towards backward point to end the over\"}]},{\"ball\":[{\"score\":1,\"timeStamp\":\"0.247 1456248022\",\"batsman\":\"Sarfraz Ahmed\",\"bowler\":\"Mohammad Sami\",\"comments\":\"A run towards third man to start the over\"},{\"boundry\":\"six\",\"score\":\"6\",\"timeStamp\":\"0.83 1456248064\",\"batsman\":\"Ahmad Shehzad\",\"bowler\":\"Mohammad Sami\",\"comments\":\"SIX! Flicked from the pads for a biggie towards backward square\"},{\"wicket\":\"catch\",\"outBatsmanByFielder1\":\"Samuel Badree\",\"score\":0,\"timeStamp\":\"0.627 1456248140\",\"batsman\":\"Ahmad Shehzad\",\"bowler\":\"Mohammad Sami\",\"comments\":\"OUT! Swept straight to the fielder at short fine leg\"},{\"score\":1,\"timeStamp\":\"0.548 1456248238\",\"batsman\":\"Grant Elliot\",\"bowler\":\"Mohammad Sami\",\"comments\":\"A run towards third man\"},{\"score\":1,\"timeStamp\":\"0.604 1456248277\",\"batsman\":\"Sarfraz Ahmed\",\"bowler\":\"Mohammad Sami\",\"comments\":\"Worked towards the leg side for a run\"},{\"ballPlayedType\":\"LegBye\",\"score\":1,\"timeStamp\":\"0.546 1456248336\",\"batsman\":\"Grant Elliot\",\"bowler\":\"Mohammad Sami\",\"comments\":\"One leg bye to end the over\"}]},{\"ball\":[{\"score\":2,\"timeStamp\":\"0.268 1456248440\",\"batsman\":\"Grant Elliot\",\"bowler\":\"Mohammad Irfan\",\"comments\":\"Top edged for a couple of runs towards third man\"},{\"score\":0,\"timeStamp\":\"0.429 1456248456\",\"batsman\":\"Grant Elliot\",\"bowler\":\"Mohammad Irfan\",\"comments\":\"Slow ball, the batsman fails to make contact\"},{\"score\":1,\"timeStamp\":\"0.427 1456248499\",\"batsman\":\"Grant Elliot\",\"bowler\":\"Mohammad Irfan\",\"comments\":\"A single towards the leg side\"},{\"wicket\":\"catch\",\"outBatsmanByFielder1\":\"Dwayne Smith\",\"score\":0,\"timeStamp\":\"0.64 1456248574\",\"batsman\":\"Sarfraz Ahmed\",\"bowler\":\"Mohammad Irfan\",\"comments\":\"OUT! Top edged in the air and the fielder takes a catch\"},{\"score\":1,\"timeStamp\":\"0.447 1456248675\",\"batsman\":\"Grant Elliot\",\"bowler\":\"Mohammad Irfan\",\"comments\":\"A quick single taken\"},{\"score\":1,\"timeStamp\":\"0.154 1456248702\",\"batsman\":\"Anwar Ali\",\"bowler\":\"Mohammad Irfan\",\"comments\":\"Guided towards third man for a run\"}]},{\"ball\":[{\"score\":0,\"timeStamp\":\"0.654 1456248776\",\"batsman\":\"Anwar Ali\",\"bowler\":\"Mohammad Sami\",\"comments\":\"Swing and a miss, dot ball. Sharp stuff\"},{\"boundry\":\"four\",\"score\":\"4\",\"timeStamp\":\"0.974 1456248816\",\"batsman\":\"Anwar Ali\",\"bowler\":\"Mohammad Sami\",\"comments\":\"FOUR! Pulled towards deep mid wicket for an important boundary\"},{\"score\":0,\"timeStamp\":\"0.917 1456248865\",\"batsman\":\"Anwar Ali\",\"bowler\":\"Mohammad Sami\",\"comments\":\"Another swing and a miss, another dot ball\"},{\"score\":0,\"timeStamp\":\"0.981 1456248933\",\"batsman\":\"Anwar Ali\",\"bowler\":\"Mohammad Sami\",\"comments\":\"Swing and a miss yet again, dot ball\"},{\"score\":0,\"timeStamp\":\"0.778 1456248980\",\"batsman\":\"Anwar Ali\",\"bowler\":\"Mohammad Sami\",\"comments\":\"Funny stuff, swing and a miss again, fourth from the over\"},{\"score\":0,\"timeStamp\":\"0.06 1456249022\",\"batsman\":\"Anwar Ali\",\"bowler\":\"Mohammad Sami\",\"comments\":\"Fifth dot delivery from the over, excellent bowling, a series of swing and misses\"}]},{\"ball\":[{\"score\":1,\"timeStamp\":\"0.814 1456249099\",\"batsman\":\"Grant Elliot\",\"bowler\":\"Andre Russell\",\"comments\":\"Inside edge for a single to start the last over\"},{\"boundry\":\"six\",\"score\":\"6\",\"timeStamp\":\"0.51 1456249141\",\"batsman\":\"Anwar Ali\",\"bowler\":\"Andre Russell\",\"comments\":\"SIX! Slower ball, slog swept for a biggie towards deep mid wicket\"},{\"score\":2,\"timeStamp\":\"0.028 1456249176\",\"batsman\":\"Anwar Ali\",\"bowler\":\"Andre Russell\",\"comments\":\"A quick couple of runs towards the leg side\"},{\"wicket\":\"catch\",\"outBatsmanByFielder1\":\"Khalid Latif\",\"score\":0,\"timeStamp\":\"0.652 1456249215\",\"batsman\":\"Anwar Ali\",\"bowler\":\"Andre Russell\",\"comments\":\"OUT! Hit hard and caught by the fielder towards the off side fence\"},{\"score\":0,\"timeStamp\":\"0.642 1456249312\",\"batsman\":\"Grant Elliot\",\"bowler\":\"Andre Russell\",\"comments\":\"Dot ball\"},{\"boundry\":\"six\",\"score\":\"6\",\"timeStamp\":\"0.774 1456249318\",\"batsman\":\"Grant Elliot\",\"bowler\":\"Andre Russell\"}]}]},\"overs\":{\"totalOvers\":20,\"bowledOvers\":20},\"batOrder\":[\"Bismillah Khan\",\"Ahmad Shehzad\",\"Kevin Pietersen\",\"Kumar Sangakkara\",\"Mohammad Nawaz\",\"Sarfraz Ahmed\",\"Grant Elliot\",\"Anwar Ali\",\"Nathan McCullum\"]},\"secondInning\":{\"batsman\":{\"Sharjeel Khan\":{\"name\":\"Sharjeel Khan\",\"bowlerStatus\":false,\"onStrick\":false,\"status\":false,\"out\":\"B Nathan McCullum\"},\"Brad Haddin\":{\"name\":\"Brad Haddin\",\"bowlerStatus\":false,\"onStrick\":true,\"status\":true},\"Dwayne Smith\":{\"name\":\"Dwayne Smith\",\"bowlerStatus\":true,\"onStrick\":false,\"status\":false,\"out\":\"C Kevin Pietersen B Zulfiqar Babar\"},\"Asif Ali\":{\"name\":\"Asif Ali\",\"bowlerStatus\":false},\"Misbah ul Haq\":{\"name\":\"Misbah ul Haq\",\"bowlerStatus\":false,\"onStrick\":false,\"status\":true},\"Samuel Badree\":{\"name\":\"Samuel Badree\",\"bowlerStatus\":false,\"wicket\":0},\"Mohammad Irfan\":{\"name\":\"Mohammad Irfan\",\"bowlerStatus\":false,\"wicket\":1},\"Imran Khalid\":{\"name\":\"Imran Khalid\",\"bowlerStatus\":false,\"wicket\":0},\"Mohammad Sami\":{\"name\":\"Mohammad Sami\",\"bowlerStatus\":false,\"wicket\":0},\"Andre Russell\":{\"name\":\"Andre Russell\",\"bowlerStatus\":false,\"wicket\":1,\"onStrick\":false,\"status\":false,\"out\":\"B Aizaz Cheema\"},\"Khalid Latif\":{\"name\":\"Khalid Latif\",\"bowlerStatus\":false,\"onStrick\":false,\"status\":false,\"out\":\"C Zulfiqar Babar B Anwar Ali\"}},\"bowler\":{\"Ahmad Shehzad\":{\"name\":\"Ahmad Shehzad\",\"onStrick\":false,\"status\":true,\"bowlerStatus\":false},\"Bismillah Khan\":{\"name\":\"Bismillah Khan\",\"onStrick\":false,\"status\":false,\"out\":\"C Brad Haddin B Mohammad Irfan\",\"bowlerStatus\":false},\"Kumar Sangakkara\":{\"name\":\"Kumar Sangakkara\",\"onStrick\":true,\"status\":true,\"bowlerStatus\":false},\"Sarfraz Ahmed\":{\"name\":\"Sarfraz Ahmed\",\"bowlerStatus\":false},\"Kevin Pietersen\":{\"name\":\"Kevin Pietersen\",\"onStrick\":false,\"status\":false,\"out\":\"C Asif Ali B Andre Russell\",\"bowlerStatus\":false},\"Grant Elliot\":{\"name\":\"Grant Elliot\",\"bowlerStatus\":false,\"wicket\":0},\"Mohammad Nawaz\":{\"name\":\"Mohammad Nawaz\",\"bowlerStatus\":false,\"wicket\":0},\"Nathan McCullum\":{\"name\":\"Nathan McCullum\",\"bowlerStatus\":false,\"wicket\":1},\"Anwar Ali\":{\"name\":\"Anwar Ali\",\"bowlerStatus\":true,\"wicket\":1},\"Zulfiqar Babar\":{\"name\":\"Zulfiqar Babar\",\"bowlerStatus\":false,\"wicket\":1},\"Aizaz Cheema\":{\"name\":\"Aizaz Cheema\",\"bowlerStatus\":false,\"wicket\":1}},\"bowls\":{\"overs\":[{\"ball\":[{\"score\":0,\"timeStamp\":\"0.785 1456250093\",\"batsman\":\"Dwayne Smith\",\"bowler\":\"Anwar Ali\",\"comments\":\"Hit on the pads, missing leg stump\"},{\"boundry\":\"four\",\"score\":\"4\",\"timeStamp\":\"0.105 1456250136\",\"batsman\":\"Dwayne Smith\",\"bowler\":\"Anwar Ali\",\"comments\":\"FOUR! Slapped towards the off side for the first boundary of the innings\"},{\"boundry\":\"four\",\"score\":\"4\",\"timeStamp\":\"0.633 1456250183\",\"batsman\":\"Dwayne Smith\",\"bowler\":\"Anwar Ali\",\"comments\":\"FOUR! Another boundary, this time towards the long on region\"},{\"score\":1,\"timeStamp\":\"0.593 1456250228\",\"batsman\":\"Dwayne Smith\",\"bowler\":\"Anwar Ali\",\"comments\":\"Tapped towards the leg side for a run\"},{\"score\":0,\"timeStamp\":\"0.177 1456250278\",\"batsman\":\"Sharjeel Khan\",\"bowler\":\"Anwar Ali\",\"comments\":\"On the pads, dot ball\"},{\"boundry\":\"six\",\"score\":\"6\",\"timeStamp\":\"0.217 1456250324\",\"batsman\":\"Sharjeel Khan\",\"bowler\":\"Anwar Ali\",\"comments\":\"SIX! Pulled away in excellent fashion for the maximum\"}]},{\"ball\":[{\"boundry\":\"four\",\"score\":\"4\",\"timeStamp\":\"0.425 1456250405\",\"batsman\":\"Dwayne Smith\",\"bowler\":\"Nathan McCullum\",\"comments\":\"FOUR! Reverse swept very fine for a boundary towards third man\"},{\"score\":0,\"timeStamp\":\"0.123 1456250426\",\"batsman\":\"Dwayne Smith\",\"bowler\":\"Nathan McCullum\"},{\"score\":0,\"timeStamp\":\"0.307 1456250602\",\"batsman\":\"Dwayne Smith\",\"bowler\":\"Nathan McCullum\"},{\"boundry\":\"four\",\"score\":\"4\",\"timeStamp\":\"0.088 1456250603\",\"batsman\":\"Dwayne Smith\",\"bowler\":\"Nathan McCullum\"},{\"score\":0,\"timeStamp\":\"0.339 1456250604\",\"batsman\":\"Dwayne Smith\",\"bowler\":\"Nathan McCullum\"},{\"score\":1,\"timeStamp\":\"0.104 1456250614\",\"batsman\":\"Dwayne Smith\",\"bowler\":\"Nathan McCullum\"}]},{\"ball\":[{\"score\":1,\"timeStamp\":\"0.314 1456250632\",\"batsman\":\"Dwayne Smith\",\"bowler\":\"Anwar Ali\"},{\"score\":1,\"timeStamp\":\"0.714 1456250639\",\"batsman\":\"Sharjeel Khan\",\"bowler\":\"Anwar Ali\"},{\"score\":0,\"timeStamp\":\"0.498 1456250682\",\"batsman\":\"Dwayne Smith\",\"bowler\":\"Anwar Ali\",\"comments\":\"Bouncer, left alone by the batsman\"},{\"boundry\":\"six\",\"score\":\"6\",\"timeStamp\":\"0.139 1456250730\",\"batsman\":\"Dwayne Smith\",\"bowler\":\"Anwar Ali\",\"comments\":\"SIX! Lofted over deep mid wicket for the maximum\"},{\"score\":0,\"timeStamp\":\"0.794 1456250771\",\"batsman\":\"Dwayne Smith\",\"bowler\":\"Anwar Ali\",\"comments\":\"Cut away, but straight to the fielder\"},{\"score\":0,\"timeStamp\":\"0.57 1456250817\",\"batsman\":\"Dwayne Smith\",\"bowler\":\"Anwar Ali\",\"comments\":\"Yorker, dot delivery\"}]},{\"ball\":[{\"score\":0,\"timeStamp\":\"0.179 1456250891\",\"batsman\":\"Sharjeel Khan\",\"bowler\":\"Nathan McCullum\",\"comments\":\"A dot delivery to start the over\"},{\"score\":1,\"timeStamp\":\"0.593 1456250904\",\"batsman\":\"Sharjeel Khan\",\"bowler\":\"Nathan McCullum\",\"comments\":\"Worked towards long on for a run\"},{\"boundry\":\"four\",\"score\":\"4\",\"timeStamp\":\"0.187 1456250939\",\"batsman\":\"Dwayne Smith\",\"bowler\":\"Nathan McCullum\",\"comments\":\"FOUR! Inside edge for a lucky boundary\"},{\"score\":1,\"timeStamp\":\"0.201 1456250974\",\"batsman\":\"Dwayne Smith\",\"bowler\":\"Nathan McCullum\",\"comments\":\"Played towards long on for a run\"},{\"score\":1,\"timeStamp\":\"0.563 1456251067\",\"batsman\":\"Sharjeel Khan\",\"bowler\":\"Nathan McCullum\",\"comments\":\"A single towards the leg side\"},{\"score\":1,\"timeStamp\":\"0.809 1456251126\",\"batsman\":\"Dwayne Smith\",\"bowler\":\"Nathan McCullum\",\"comments\":\"A run down the ground to end the over\"}]},{\"ball\":[{\"score\":0,\"timeStamp\":\"0.594 1456251154\",\"batsman\":\"Dwayne Smith\",\"bowler\":\"Aizaz Cheema\",\"comments\":\"Played towards the bowler, dot ball\"},{\"score\":1,\"timeStamp\":\"0.842 1456251171\",\"batsman\":\"Dwayne Smith\",\"bowler\":\"Aizaz Cheema\",\"comments\":\"A run taken towards the leg side\"},{\"score\":0,\"timeStamp\":\"0.394 1456251229\",\"batsman\":\"Sharjeel Khan\",\"bowler\":\"Aizaz Cheema\",\"comments\":\"Played towards the fielder, dot ball\"},{\"boundry\":\"four\",\"score\":\"4\",\"timeStamp\":\"0.186 1456251273\",\"batsman\":\"Sharjeel Khan\",\"bowler\":\"Aizaz Cheema\",\"comments\":\"FOUR! Flicked from the pads for a boundary towards backward square\"},{\"ballPlayedType\":\"LegBye\",\"score\":1,\"timeStamp\":\"0.523 1456251335\",\"batsman\":\"Sharjeel Khan\",\"bowler\":\"Aizaz Cheema\",\"comments\":\"On the pads, one leg bye\"},{\"score\":0,\"timeStamp\":\"0.378 1456251372\",\"batsman\":\"Dwayne Smith\",\"bowler\":\"Aizaz Cheema\",\"comments\":\"A dot delivery to end the over\"}]},{\"ball\":[{\"ballPlayedType\":\"LegBye\",\"score\":1,\"timeStamp\":\"0.026 1456251432\",\"batsman\":\"Sharjeel Khan\",\"bowler\":\"Nathan McCullum\",\"comments\":\"Swept away, one leg bye\"},{\"boundry\":\"six\",\"score\":\"6\",\"timeStamp\":\"0.915 1456251448\",\"batsman\":\"Dwayne Smith\",\"bowler\":\"Nathan McCullum\",\"comments\":\"SIX! Lofted towards long on for the maximum\"},{\"score\":1,\"timeStamp\":\"0.154 1456251476\",\"batsman\":\"Dwayne Smith\",\"bowler\":\"Nathan McCullum\",\"comments\":\"A quick single taken towards short cover\"},{\"wicket\":\"bowled\",\"score\":\"0\",\"timeStamp\":\"0.257 1456251511\",\"batsman\":\"Sharjeel Khan\",\"bowler\":\"Nathan McCullum\",\"comments\":\"OUT! The batsman is bowled off a slow delivery\"},{\"score\":1,\"timeStamp\":\"0.588 1456251620\",\"batsman\":\"Brad Haddin\",\"bowler\":\"Nathan McCullum\",\"comments\":\"A single to open the account\"},{\"score\":0,\"timeStamp\":\"0.379 1456251624\",\"batsman\":\"Dwayne Smith\",\"bowler\":\"Nathan McCullum\",\"comments\":\"Dot delivery to end the over\"}]},{\"ball\":[{\"score\":1,\"timeStamp\":\"0.091 1456251722\",\"batsman\":\"Brad Haddin\",\"bowler\":\"Zulfiqar Babar\",\"comments\":\"A single towards short third man\"},{\"score\":0,\"timeStamp\":\"0.515 1456251724\",\"batsman\":\"Dwayne Smith\",\"bowler\":\"Zulfiqar Babar\",\"comments\":\"Dot delivery\"},{\"boundry\":\"six\",\"score\":\"6\",\"timeStamp\":\"0.77 1456251747\",\"batsman\":\"Dwayne Smith\",\"bowler\":\"Zulfiqar Babar\",\"comments\":\"SIX! Flicked towards the leg side over square leg for the maximum\"},{\"score\":0,\"timeStamp\":\"0.274 1456251791\",\"batsman\":\"Dwayne Smith\",\"bowler\":\"Zulfiqar Babar\",\"comments\":\"A dot ball\"},{\"score\":1,\"timeStamp\":\"0.459 1456251808\",\"batsman\":\"Dwayne Smith\",\"bowler\":\"Zulfiqar Babar\",\"comments\":\"Played towards long off for a run\"},{\"boundry\":\"four\",\"score\":\"4\",\"timeStamp\":\"0.267 1456251835\",\"batsman\":\"Brad Haddin\",\"bowler\":\"Zulfiqar Babar\"}]},{\"ball\":[{\"score\":0,\"timeStamp\":\"0.283 1456252141\",\"batsman\":\"Dwayne Smith\",\"bowler\":\"Mohammad Nawaz\"},{\"score\":1,\"timeStamp\":\"0.988 1456252141\",\"batsman\":\"Dwayne Smith\",\"bowler\":\"Mohammad Nawaz\"},{\"score\":0,\"timeStamp\":\"0.842 1456252142\",\"batsman\":\"Brad Haddin\",\"bowler\":\"Mohammad Nawaz\"},{\"score\":0,\"timeStamp\":\"0.34 1456252143\",\"batsman\":\"Brad Haddin\",\"bowler\":\"Mohammad Nawaz\"},{\"score\":0,\"timeStamp\":\"0.627 1456252143\",\"batsman\":\"Brad Haddin\",\"bowler\":\"Mohammad Nawaz\"},{\"score\":0,\"timeStamp\":\"0.994 1456252149\",\"batsman\":\"Brad Haddin\",\"bowler\":\"Mohammad Nawaz\"}]},{\"ball\":[{\"score\":0,\"timeStamp\":\"0.371 1456252179\",\"batsman\":\"Dwayne Smith\",\"bowler\":\"Grant Elliot\",\"comments\":\"Slow ball, dot delivery\"},{\"boundry\":\"four\",\"score\":\"4\",\"timeStamp\":\"0.972 1456252204\",\"batsman\":\"Dwayne Smith\",\"bowler\":\"Grant Elliot\",\"comments\":\"FOUR! A welcome boundary for the Gladiators\"},{\"score\":1,\"timeStamp\":\"0.899 1456252231\",\"batsman\":\"Dwayne Smith\",\"bowler\":\"Grant Elliot\",\"comments\":\"A run down the ground\"},{\"boundry\":\"six\",\"score\":\"6\",\"timeStamp\":\"0.066 1456252276\",\"batsman\":\"Brad Haddin\",\"bowler\":\"Grant Elliot\",\"comments\":\"SIX! Played towards deep mid wicket for the  maximum\"},{\"score\":0,\"timeStamp\":\"0.938 1456252308\",\"batsman\":\"Brad Haddin\",\"bowler\":\"Grant Elliot\",\"comments\":\"Blocked, no runs\"},{\"score\":0,\"timeStamp\":\"0.37 1456252331\",\"batsman\":\"Brad Haddin\",\"bowler\":\"Grant Elliot\",\"comments\":\"Hit towards the bowler, dot ball\"}]},{\"ball\":[{\"score\":1,\"timeStamp\":\"0.668 1456252413\",\"batsman\":\"Dwayne Smith\",\"bowler\":\"Mohammad Nawaz\",\"comments\":\"DROPPED. The batsman is dropped in the deep\"},{\"score\":0,\"timeStamp\":\"0.275 1456252445\",\"batsman\":\"Brad Haddin\",\"bowler\":\"Mohammad Nawaz\",\"comments\":\"Blocked for no runs\"},{\"score\":1,\"timeStamp\":\"0.923 1456252477\",\"batsman\":\"Brad Haddin\",\"bowler\":\"Mohammad Nawaz\",\"comments\":\"A quick run towards short third man\"},{\"score\":0,\"timeStamp\":\"0.516 1456252517\",\"batsman\":\"Dwayne Smith\",\"bowler\":\"Mohammad Nawaz\",\"comments\":\"Good ball, defended for nothing\"},{\"score\":1,\"timeStamp\":\"0.274 1456252543\",\"batsman\":\"Dwayne Smith\",\"bowler\":\"Mohammad Nawaz\",\"comments\":\"Tapped towards the off side for a run\"},{\"score\":1,\"timeStamp\":\"0.09 1456252589\",\"batsman\":\"Brad Haddin\",\"bowler\":\"Mohammad Nawaz\",\"comments\":\"A run towards short third man to end the over\"}]},{\"ball\":[{\"score\":1,\"timeStamp\":\"0.284 1456252704\",\"batsman\":\"Brad Haddin\",\"bowler\":\"Aizaz Cheema\",\"comments\":\"A quick single towards short third man\"},{\"boundry\":\"four\",\"score\":\"4\",\"timeStamp\":\"0.498 1456252744\",\"batsman\":\"Dwayne Smith\",\"bowler\":\"Aizaz Cheema\",\"comments\":\"FOUR!  Flicked from the pads for a boundary towards backward square\"},{\"score\":1,\"timeStamp\":\"0.219 1456252800\",\"batsman\":\"Dwayne Smith\",\"bowler\":\"Aizaz Cheema\",\"comments\":\"A quick single taken\"},{\"score\":0,\"timeStamp\":\"0.602 1456252845\",\"batsman\":\"Brad Haddin\",\"bowler\":\"Aizaz Cheema\",\"comments\":\"A dot delivery\"},{\"boundry\":\"four\",\"score\":\"4\",\"timeStamp\":\"0.267 1456252911\",\"batsman\":\"Brad Haddin\",\"bowler\":\"Aizaz Cheema\",\"comments\":\"FOUR! Hit straight down the ground and  some poor fielding costs a boundary\"},{\"score\":1,\"timeStamp\":\"0.507 1456252969\",\"batsman\":\"Brad Haddin\",\"bowler\":\"Aizaz Cheema\",\"comments\":\"A run towards long off to end the over\"}]},{\"ball\":[{\"score\":1,\"timeStamp\":\"0.876 1456253072\",\"batsman\":\"Brad Haddin\",\"bowler\":\"Mohammad Nawaz\",\"comments\":\"The batsman comes down the track and takes a run towards the off side\"},{\"score\":0,\"timeStamp\":\"0.964 1456253107\",\"batsman\":\"Dwayne Smith\",\"bowler\":\"Mohammad Nawaz\",\"comments\":\"Quicker delivery, dot ball\"},{\"score\":1,\"timeStamp\":\"0.731 1456253133\",\"batsman\":\"Dwayne Smith\",\"bowler\":\"Mohammad Nawaz\",\"comments\":\"DROPPED. A chance has been put down, a sharp one\"},{\"boundry\":\"six\",\"score\":\"6\",\"timeStamp\":\"0.611 1456253173\",\"batsman\":\"Brad Haddin\",\"bowler\":\"Mohammad Nawaz\",\"comments\":\"SIX! Lofted down the ground for a huge six\"},{\"score\":1,\"timeStamp\":\"0.875 1456253252\",\"batsman\":\"Brad Haddin\",\"bowler\":\"Mohammad Nawaz\",\"comments\":\"A quick run towards short third man\"},{\"score\":1,\"timeStamp\":\"0.05 1456253282\",\"batsman\":\"Dwayne Smith\",\"bowler\":\"Mohammad Nawaz\",\"comments\":\"A single down the ground to end the over\"}]},{\"ball\":[{\"score\":1,\"timeStamp\":\"0.94 1456253351\",\"batsman\":\"Dwayne Smith\",\"bowler\":\"Grant Elliot\",\"comments\":\"A run towards deep mid wicket to start the over\"},{\"score\":2,\"timeStamp\":\"0.691 1456253408\",\"batsman\":\"Brad Haddin\",\"bowler\":\"Grant Elliot\",\"comments\":\"Hit down the ground for a couple of runs\"},{\"boundry\":\"six\",\"score\":\"6\",\"timeStamp\":\"0.203 1456253469\",\"batsman\":\"Brad Haddin\",\"bowler\":\"Grant Elliot\",\"comments\":\"SIX! A biggie down the ground over long on\"},{\"score\":1,\"timeStamp\":\"0.002 1456253498\",\"batsman\":\"Brad Haddin\",\"bowler\":\"Grant Elliot\",\"comments\":\"A single towards long on to rotate strike\"},{\"score\":0,\"timeStamp\":\"0.85 1456253526\",\"batsman\":\"Dwayne Smith\",\"bowler\":\"Grant Elliot\",\"comments\":\"Slower bouncer, dot ball\"},{\"boundry\":\"six\",\"score\":\"6\",\"timeStamp\":\"0.026 1456253563\",\"batsman\":\"Dwayne Smith\",\"bowler\":\"Grant Elliot\",\"comments\":\"SIX! Slapped over long on for a massive hit to end the over\"}]},{\"ball\":[{\"score\":0,\"timeStamp\":\"0.699 1456253654\",\"batsman\":\"Brad Haddin\",\"bowler\":\"Zulfiqar Babar\",\"comments\":\"Sharp spin on offer, dot ball\"},{\"score\":1,\"timeStamp\":\"0.187 1456253675\",\"batsman\":\"Brad Haddin\",\"bowler\":\"Zulfiqar Babar\",\"comments\":\"A run towards short third man\"},{\"score\":1,\"timeStamp\":\"0.299 1456253699\",\"batsman\":\"Dwayne Smith\",\"bowler\":\"Zulfiqar Babar\",\"comments\":\"Played towards off side for a run\"},{\"score\":1,\"timeStamp\":\"0.468 1456253724\",\"batsman\":\"Brad Haddin\",\"bowler\":\"Zulfiqar Babar\",\"comments\":\"A run towards the leg side\"},{\"score\":1,\"timeStamp\":\"0.986 1456253756\",\"batsman\":\"Dwayne Smith\",\"bowler\":\"Zulfiqar Babar\",\"comments\":\"A run down the ground\"},{\"boundry\":\"six\",\"score\":\"6\",\"timeStamp\":\"0.434 1456253794\",\"batsman\":\"Brad Haddin\",\"bowler\":\"Zulfiqar Babar\",\"comments\":\"SIX! Swept away towards square leg for a maximum\"}]},{\"ball\":[{\"score\":1,\"timeStamp\":\"0.935 1456254120\",\"batsman\":\"Dwayne Smith\",\"bowler\":\"Aizaz Cheema\",\"comments\":\"A single towards the leg side to start the over\"},{\"score\":1,\"timeStamp\":\"0.122 1456254143\",\"batsman\":\"Brad Haddin\",\"bowler\":\"Aizaz Cheema\",\"comments\":\"A run towards the off side\"},{\"score\":1,\"timeStamp\":\"0.156 1456254193\",\"batsman\":\"Dwayne Smith\",\"bowler\":\"Aizaz Cheema\",\"comments\":\"Inside edge for third run in the over\"},{\"score\":1,\"timeStamp\":\"0.492 1456254593\",\"batsman\":\"Brad Haddin\",\"bowler\":\"Aizaz Cheema\"},{\"ballPlayedType\":\"LegBye\",\"score\":1,\"timeStamp\":\"0.059 1456254603\",\"batsman\":\"Dwayne Smith\",\"bowler\":\"Aizaz Cheema\"},{\"score\":2,\"timeStamp\":\"0.219 1456254610\",\"batsman\":\"Brad Haddin\",\"bowler\":\"Aizaz Cheema\"}]},{\"ball\":[{\"score\":1,\"timeStamp\":\"0.426 1456254621\",\"batsman\":\"Dwayne Smith\",\"bowler\":\"Zulfiqar Babar\"},{\"score\":1,\"timeStamp\":\"0.258 1456254622\",\"batsman\":\"Brad Haddin\",\"bowler\":\"Zulfiqar Babar\"},{\"wicket\":\"catch\",\"outBatsmanByFielder1\":\"Kevin Pietersen\",\"score\":0,\"timeStamp\":\"0.193 1456254637\",\"batsman\":\"Dwayne Smith\",\"bowler\":\"Zulfiqar Babar\"},{\"score\":1,\"timeStamp\":\"0.715 1456254653\",\"batsman\":\"Brad Haddin\",\"bowler\":\"Zulfiqar Babar\"},{\"boundry\":\"six\",\"score\":\"6\",\"timeStamp\":\"0.162 1456254666\",\"batsman\":\"Andre Russell\",\"bowler\":\"Zulfiqar Babar\"},{\"score\":1,\"timeStamp\":\"0.491 1456254681\",\"batsman\":\"Andre Russell\",\"bowler\":\"Zulfiqar Babar\"}]},{\"ball\":[{\"wicket\":\"bowled\",\"score\":\"0\",\"timeStamp\":\"0.137 1456254765\",\"batsman\":\"Andre Russell\",\"bowler\":\"Aizaz Cheema\",\"comments\":\"OUT! Slow ball, the batsman is bowled. Big wicket\"},{\"score\":1,\"timeStamp\":\"0.26 1456254870\",\"batsman\":\"Khalid Latif\",\"bowler\":\"Aizaz Cheema\",\"comments\":\"A run down the ground to open the account\"},{\"score\":1,\"timeStamp\":\"0.259 1456254911\",\"batsman\":\"Brad Haddin\",\"bowler\":\"Aizaz Cheema\",\"comments\":\"A run towards short third man\"},{\"boundry\":\"four\",\"score\":\"4\",\"timeStamp\":\"0.867 1456254966\",\"batsman\":\"Khalid Latif\",\"bowler\":\"Aizaz Cheema\",\"comments\":\"FOUR! Hit down the ground for a boundary\"},{\"score\":2,\"timeStamp\":\"0.707 1456255011\",\"batsman\":\"Khalid Latif\",\"bowler\":\"Aizaz Cheema\",\"comments\":\"Pulled towards the leg side for a couple\"},{\"boundry\":\"four\",\"score\":\"4\",\"timeStamp\":\"0.738 1456255055\",\"batsman\":\"Khalid Latif\",\"bowler\":\"Aizaz Cheema\",\"comments\":\"FOUR! Smoked towards extra cover for a boundary\"}]},{\"ball\":[{\"boundry\":\"six\",\"score\":\"6\",\"timeStamp\":\"0.091 1456255133\",\"batsman\":\"Brad Haddin\",\"bowler\":\"Zulfiqar Babar\",\"comments\":\"SIX! Slog swept towards mid wicket for the maximum\"},{\"score\":2,\"timeStamp\":\"0.986 1456255166\",\"batsman\":\"Brad Haddin\",\"bowler\":\"Zulfiqar Babar\",\"comments\":\"Played towards the off side for a couple\"},{\"ballPlayedType\":\"LegBye\",\"score\":1,\"timeStamp\":\"0.059 1456255209\",\"batsman\":\"Brad Haddin\",\"bowler\":\"Zulfiqar Babar\",\"comments\":\"Padded away for a run\"},{\"score\":1,\"timeStamp\":\"0.523 1456255227\",\"batsman\":\"Khalid Latif\",\"bowler\":\"Zulfiqar Babar\",\"comments\":\"A run towards extra cover\"},{\"score\":0,\"timeStamp\":\"0.011 1456255245\",\"batsman\":\"Brad Haddin\",\"bowler\":\"Zulfiqar Babar\",\"comments\":\"Played towards the bowler, dot ball\"},{\"score\":0,\"timeStamp\":\"0.389 1456255266\",\"batsman\":\"Brad Haddin\",\"bowler\":\"Zulfiqar Babar\",\"comments\":\"Inside edge, and no runs to end the over\"}]},{\"ball\":[{\"boundry\":\"four\",\"score\":\"4\",\"timeStamp\":\"0.754 1456255337\",\"batsman\":\"Khalid Latif\",\"bowler\":\"Anwar Ali\",\"comments\":\"FOUR! Lofted towards deep mid wicket for a boundary, only a matter of time now\"},{\"wicket\":\"catch\",\"outBatsmanByFielder1\":\"Zulfiqar Babar\",\"score\":0,\"timeStamp\":\"0.017 1456255387\",\"batsman\":\"Khalid Latif\",\"bowler\":\"Anwar Ali\",\"comments\":\"OUT! Caught by the fielder towards fine leg\"},{\"score\":1,\"timeStamp\":\"0.5 1456255460\",\"batsman\":\"Brad Haddin\",\"bowler\":\"Anwar Ali\",\"comments\":\"A single towards fine leg, scores level\"},{\"comments\":\"And that is it! Misbah hits the winning runs and Islamabad United have won the first edition of the PSL\",\"score\":1,\"timeStamp\":\"0.853 1456255530\",\"batsman\":\"Misbah ul Haq\",\"bowler\":\"Anwar Ali\"}]}]},\"overs\":{\"totalOvers\":20,\"bowledOvers\":18.4},\"target\":174,\"batOrder\":[\"Sharjeel Khan\",\"Dwayne Smith\",\"Brad Haddin\",\"Andre Russell\",\"Khalid Latif\",\"Misbah ul Haq\"]},\"superOverFirstInning\":{\"batsman\":{\"Ahmad Shehzad\":{\"name\":\"Ahmad Shehzad\"},\"Bismillah Khan\":{\"name\":\"Bismillah Khan\"},\"Kumar Sangakkara\":{\"name\":\"Kumar Sangakkara\"},\"Sarfraz Ahmed\":{\"name\":\"Sarfraz Ahmed\"},\"Kevin Pietersen\":{\"name\":\"Kevin Pietersen\"},\"Grant Elliot\":{\"name\":\"Grant Elliot\"},\"Mohammad Nawaz\":{\"name\":\"Mohammad Nawaz\"},\"Nathan McCullum\":{\"name\":\"Nathan McCullum\"},\"Anwar Ali\":{\"name\":\"Anwar Ali\"},\"Zulfiqar Babar\":{\"name\":\"Zulfiqar Babar\"},\"Aizaz Cheema\":{\"name\":\"Aizaz Cheema\"}},\"bowler\":{\"Sharjeel Khan\":{\"name\":\"Sharjeel Khan\"},\"Brad Haddin\":{\"name\":\"Brad Haddin\"},\"Dwayne Smith\":{\"name\":\"Dwayne Smith\"},\"Asif Ali\":{\"name\":\"Asif Ali\"},\"Misbah ul Haq\":{\"name\":\"Misbah ul Haq\"},\"Samuel Badree\":{\"name\":\"Samuel Badree\"},\"Mohammad Irfan\":{\"name\":\"Mohammad Irfan\"},\"Imran Khalid\":{\"name\":\"Imran Khalid\"},\"Mohammad Sami\":{\"name\":\"Mohammad Sami\"},\"Andre Russell\":{\"name\":\"Andre Russell\"},\"Khalid Latif\":{\"name\":\"Khalid Latif\"}},\"bowls\":{\"overs\":[]},\"overs\":{\"totalOvers\":1,\"bowledOvers\":0},\"batOrder\":[]},\"superOverSecondInning\":{\"batsman\":{\"Sharjeel Khan\":{\"name\":\"Sharjeel Khan\"},\"Brad Haddin\":{\"name\":\"Brad Haddin\"},\"Dwayne Smith\":{\"name\":\"Dwayne Smith\"},\"Asif Ali\":{\"name\":\"Asif Ali\"},\"Misbah ul Haq\":{\"name\":\"Misbah ul Haq\"},\"Samuel Badree\":{\"name\":\"Samuel Badree\"},\"Mohammad Irfan\":{\"name\":\"Mohammad Irfan\"},\"Imran Khalid\":{\"name\":\"Imran Khalid\"},\"Mohammad Sami\":{\"name\":\"Mohammad Sami\"},\"Andre Russell\":{\"name\":\"Andre Russell\"},\"Khalid Latif\":{\"name\":\"Khalid Latif\"}},\"bowler\":{\"Ahmad Shehzad\":{\"name\":\"Ahmad Shehzad\"},\"Bismillah Khan\":{\"name\":\"Bismillah Khan\"},\"Kumar Sangakkara\":{\"name\":\"Kumar Sangakkara\"},\"Sarfraz Ahmed\":{\"name\":\"Sarfraz Ahmed\"},\"Kevin Pietersen\":{\"name\":\"Kevin Pietersen\"},\"Grant Elliot\":{\"name\":\"Grant Elliot\"},\"Mohammad Nawaz\":{\"name\":\"Mohammad Nawaz\"},\"Nathan McCullum\":{\"name\":\"Nathan McCullum\"},\"Anwar Ali\":{\"name\":\"Anwar Ali\"},\"Zulfiqar Babar\":{\"name\":\"Zulfiqar Babar\"},\"Aizaz Cheema\":{\"name\":\"Aizaz Cheema\"}},\"bowls\":{\"overs\":[]},\"overs\":{\"totalOvers\":1,\"bowledOvers\":0},\"target\":0,\"batOrder\":[]},\"activeInning\":{\"firstInning\":false,\"secondInning\":true,\"superOverFirstInning\":false,\"superOverSecondInning\":false},\"matchResults\":{\"winningTeam\":false,\"wonBy\":false,\"duckLevis\":false,\"superOver\":false},\"matchComments\":{\"tossComments\":false,\"resultComments\":false},\"TeamAName\":\"Quetta Gladiators\",\"TeamBName\":\"Islamabad United\"}","team_a_scoreboard":"{\"Ahmad Shehzad\":{\"name\":\"Ahmad Shehzad\",\"onStrick\":false,\"status\":true},\"Bismillah Khan\":{\"name\":\"Bismillah Khan\",\"onStrick\":false,\"status\":false,\"out\":\"C Brad Haddin B Mohammad Irfan\"},\"Kumar Sangakkara\":{\"name\":\"Kumar Sangakkara\",\"onStrick\":true,\"status\":true},\"Sarfraz Ahmed\":{\"name\":\"Sarfraz Ahmed\"},\"Kevin Pietersen\":{\"name\":\"Kevin Pietersen\",\"onStrick\":false,\"status\":false,\"out\":\"C Asif Ali B Andre Russell\"},\"Grant Elliot\":{\"name\":\"Grant Elliot\"},\"Mohammad Nawaz\":{\"name\":\"Mohammad Nawaz\"},\"Nathan McCullum\":{\"name\":\"Nathan McCullum\"},\"Anwar Ali\":{\"name\":\"Anwar Ali\"},\"Zulfiqar Babar\":{\"name\":\"Zulfiqar Babar\"},\"Aizaz Cheema\":{\"name\":\"Aizaz Cheema\"}}","team_b_scoreboard":"{\"Sharjeel Khan\":{\"name\":\"Sharjeel Khan\",\"bowlerStatus\":false},\"Brad Haddin\":{\"name\":\"Brad Haddin\",\"bowlerStatus\":false},\"Dwayne Smith\":{\"name\":\"Dwayne Smith\",\"bowlerStatus\":true},\"Asif Ali\":{\"name\":\"Asif Ali\",\"bowlerStatus\":false},\"Misbah ul Haq\":{\"name\":\"Misbah ul Haq\",\"bowlerStatus\":false},\"Samuel Badree\":{\"name\":\"Samuel Badree\",\"bowlerStatus\":false,\"wicket\":0},\"Mohammad Irfan\":{\"name\":\"Mohammad Irfan\",\"bowlerStatus\":false,\"wicket\":1},\"Imran Khalid\":{\"name\":\"Imran Khalid\",\"bowlerStatus\":false,\"wicket\":0},\"Mohammad Sami\":{\"name\":\"Mohammad Sami\",\"bowlerStatus\":false,\"wicket\":0},\"Andre Russell\":{\"name\":\"Andre Russell\",\"bowlerStatus\":false,\"wicket\":1},\"Khalid Latif\":{\"name\":\"Khalid Latif\",\"bowlerStatus\":false}}","match_title":"FINAL","match_date_start":null,"match_date_end":null,"match_tbd":null,"match_teamA_image":"1453111043838-team.png","match_teamB_image":"1453111086101-team.png","match_status":"Islamabad United Won by 6 wickets","teams":[{"id":"2C6999C9-8A5C-4A19-B37F-BAB963EA2CE0","__createdAt":"2016-01-01T06:40:16.609Z","__updatedAt":"2016-02-19T12:23:26.983Z","__version":{"0":0,"1":0,"2":0,"3":0,"4":0,"5":13,"6":60,"7":185,"length":8},"__deleted":false,"team_image":"1453111043838-team.png","team_name":"Quetta Gladiators","team_players_Select":null,"team_seo_title":"Quetta Gladiators","team_seo_keyword":null,"team_url":"quetta-gladiators","team_visibility":"true","team_seo_description":"Quetta Gladiators - Shan-e-Pakistan","teamPlayers":null,"team_players_name":"{\"Akbar ur Rehman\":{\"id\":\"390931AD-A410-494C-BA29-526FA2EE4A90\",\"player_name\":\"Akbar ur Rehman\",\"player_country\":\"Pakistan\",\"player_type\":\"alrounder\",\"player_captain\":null,\"player_cost\":100000,\"player_image\":\"1455113039687-player.png\",\"player_seo_title\":\"Akbar Ur Rehman\",\"player_seo_keyword\":null,\"player_url\":\"akbar-ur-rehman\",\"player_visibility\":\"true\",\"player_keeper\":null,\"player_seo_description\":null,\"player_description\":\"\"},\"M. Nabi\":{\"id\":\"A9ED59A1-CFB3-4055-85E3-D0D37E23C367\",\"player_name\":\"M. Nabi\",\"player_country\":\"Afghanistan\",\"player_type\":\"alrounder\",\"player_captain\":null,\"player_cost\":200000,\"player_image\":\"1455113069285-player.png\",\"player_seo_title\":\"Mohammad Nabi\",\"player_seo_keyword\":null,\"player_url\":\"mohammad-nabi\",\"player_visibility\":\"true\",\"player_keeper\":null,\"player_seo_description\":null,\"player_description\":\"\"},\"Asad Shafiq\":{\"id\":\"AFEEA7F8-51F1-4C28-82D7-52163EB349FC\",\"player_name\":\"Asad Shafiq\",\"player_country\":\"Pakistan\",\"player_type\":\"batsman\",\"player_captain\":null,\"player_cost\":200000,\"player_image\":\"1455113123157-player.png\",\"player_seo_title\":\"Asad Shafiq\",\"player_seo_keyword\":null,\"player_url\":\"asad-shafiq\",\"player_visibility\":\"true\",\"player_keeper\":null,\"player_seo_description\":null,\"player_description\":\"\"},\"Saad Nasim\":{\"id\":\"83433197-843D-49E1-B88B-EA52053F79DE\",\"player_name\":\"Saad Nasim\",\"player_country\":\"Pakistan\",\"player_type\":\"alrounder\",\"player_captain\":null,\"player_cost\":200000,\"player_image\":\"1455113143442-player.png\",\"player_seo_title\":\"Saad Nasim\",\"player_seo_keyword\":null,\"player_url\":\"saad-nasim\",\"player_visibility\":\"true\",\"player_keeper\":null,\"player_seo_description\":null,\"player_description\":\"\"},\"Elton Chigumbura\":{\"id\":\"E3AC954B-384F-4B2D-BF15-3417D1DD95F4\",\"player_name\":\"Elton Chigumbura\",\"player_country\":\"Zimbabwe\",\"player_type\":\"alrounder\",\"player_captain\":null,\"player_cost\":300000,\"player_image\":\"1455113181028-player.png\",\"player_seo_title\":\"Elton Chigumbura\",\"player_seo_keyword\":null,\"player_url\":\"elton-chigumbura\",\"player_visibility\":\"true\",\"player_keeper\":null,\"player_seo_description\":null,\"player_description\":\"\"},\"Zulfiqar Babar\":{\"id\":\"141F0438-CEB2-4077-AF10-04E3695F9907\",\"player_name\":\"Zulfiqar Babar\",\"player_country\":\"Pakistan\",\"player_type\":\"bowler\",\"player_captain\":\"Zulfiqar Babar\",\"player_cost\":300000,\"player_image\":\"1455113231627-player.png\",\"player_seo_title\":\"Zulfiqar Babar\",\"player_seo_keyword\":null,\"player_url\":\"zulfiqar-babar\",\"player_visibility\":\"true\",\"player_keeper\":null,\"player_seo_description\":null,\"player_description\":\"\"},\"Bilal Asif\":{\"id\":\"23AE28D3-CC70-40DA-BD91-B5B64D029930\",\"player_name\":\"Bilal Asif\",\"player_country\":\"Pakistan\",\"player_type\":\"alrounder\",\"player_captain\":null,\"player_cost\":200000,\"player_image\":\"1455113158938-player.png\",\"player_seo_title\":\"Bilal Asif\",\"player_seo_keyword\":null,\"player_url\":\"bilal-asif\",\"player_visibility\":\"true\",\"player_keeper\":null,\"player_seo_description\":null,\"player_description\":\"\"},\"Umar Gul\":{\"id\":\"5637E163-5713-40A4-BE8B-A074AB3C34C8\",\"player_name\":\"Umar Gul\",\"player_country\":\"Pakistan\",\"player_type\":\"bowler\",\"player_captain\":null,\"player_cost\":300000,\"player_image\":\"1455113257329-player.png\",\"player_seo_title\":\"Umar Gul\",\"player_seo_keyword\":null,\"player_url\":\"umar-gul\",\"player_visibility\":\"true\",\"player_keeper\":null,\"player_seo_description\":null,\"player_description\":\"\"},\"Anwar Ali\":{\"id\":\"FAED9F78-AED7-4C32-8BEB-D10497ECA60A\",\"player_name\":\"Anwar Ali\",\"player_country\":\"Pakistan\",\"player_type\":\"alrounder\",\"player_captain\":null,\"player_cost\":400000,\"player_image\":\"1455113300602-player.png\",\"player_seo_title\":\"Anwar Ali\",\"player_seo_keyword\":null,\"player_url\":\"anwar-ali\",\"player_visibility\":\"true\",\"player_keeper\":null,\"player_seo_description\":null,\"player_description\":\"\"},\"Mohammad Nawaz\":{\"id\":\"603CD383-43B1-42F9-8CC6-E83222AA006C\",\"player_name\":\"Mohammad Nawaz\",\"player_country\":\"Pakistan\",\"player_type\":\"alrounder\",\"player_captain\":null,\"player_cost\":200000,\"player_image\":\"1455113102692-player.png\",\"player_seo_title\":\"Mohammad Nawaz\",\"player_seo_keyword\":null,\"player_url\":\"mohammad-nawaz\",\"player_visibility\":\"true\",\"player_keeper\":null,\"player_seo_description\":null,\"player_description\":\"\"},\"Bismillah Khan\":{\"id\":\"14C0D271-F243-494A-96D5-0492DA255C24\",\"player_name\":\"Bismillah Khan\",\"player_country\":\"Pakistan\",\"player_type\":\"wicket keeper\",\"player_captain\":null,\"player_cost\":100000,\"player_image\":\"1455113023914-player.png\",\"player_seo_title\":\"Bismillah Khan\",\"player_seo_keyword\":null,\"player_url\":\"bismillah-khan\",\"player_visibility\":\"true\",\"player_keeper\":null,\"player_seo_description\":null,\"player_description\":\"\"},\"Ahmad Shehzad\":{\"id\":\"AB8A7DCE-CA0E-46A0-897B-66E5AFBA2627\",\"player_name\":\"Ahmad Shehzad\",\"player_country\":\"Pakistan\",\"player_type\":\"batsman\",\"player_captain\":null,\"player_cost\":500000,\"player_image\":\"1455113343740-player.png\",\"player_seo_title\":\"Ahmed Shehzad\",\"player_seo_keyword\":null,\"player_url\":\"ahmed-shehzad\",\"player_visibility\":\"true\",\"player_keeper\":null,\"player_seo_description\":null,\"player_description\":\"\"},\"Sarfraz Ahmed\":{\"id\":\"2624D7BA-B931-40C0-A08D-1D127CC0D15B\",\"player_name\":\"Sarfraz Ahmed\",\"player_country\":\"Pakistan\",\"player_type\":\"wicket keeper\",\"player_captain\":null,\"player_cost\":500000,\"player_image\":\"1453276257521-player.jpeg\",\"player_seo_title\":\"Sarfraz Ahmed\",\"player_seo_keyword\":null,\"player_url\":\"sarfraz-ahmed\",\"player_visibility\":\"true\",\"player_keeper\":true,\"player_seo_description\":null,\"player_description\":\"\"},\"Kumar Sangakkara\":{\"id\":\"76A0E1E7-3C59-4CD2-8D08-B37FD6C7C74A\",\"player_name\":\"Kumar Sangakkara\",\"player_country\":\"Sri Lanka\",\"player_type\":\"batsman\",\"player_captain\":null,\"player_cost\":0,\"player_image\":\"1453276542236-player.jpeg\",\"player_seo_title\":\"Kumar Sangakkara\",\"player_seo_keyword\":null,\"player_url\":\"kumar-sangakkara\",\"player_visibility\":\"true\",\"player_keeper\":true,\"player_seo_description\":null,\"player_description\":\"\"},\"Luke Wright\":{\"id\":\"6805DEAA-DE70-4834-84CB-8469BEF511D0\",\"player_name\":\"Luke Wright\",\"player_country\":\"England\",\"player_type\":\"alrounder\",\"player_captain\":null,\"player_cost\":400000,\"player_image\":\"1455113324805-player.png\",\"player_seo_title\":\"Luke Wright\",\"player_seo_keyword\":null,\"player_url\":\"luke-wright\",\"player_visibility\":\"true\",\"player_keeper\":null,\"player_seo_description\":null,\"player_description\":\"\"},\"Rameez Raja Jr.\":{\"id\":\"78000521-C8A9-4D61-A65A-232664716AFE\",\"player_name\":\"Rameez Raja Jr.\",\"player_country\":\"Pakistan\",\"player_type\":\"batsman\",\"player_captain\":null,\"player_cost\":0,\"player_image\":\"1455112887038-player.png\",\"player_seo_title\":\"Rameez Raja Jr.\",\"player_seo_keyword\":null,\"player_url\":\"rameez-raja-jr\",\"player_visibility\":\"true\",\"player_keeper\":null,\"player_seo_description\":null,\"player_description\":\"\"},\"Aizaz Cheema\":{\"id\":\"041E0538-D19D-4A61-897B-F6FB45F2496F\",\"player_name\":\"Aizaz Cheema\",\"player_country\":\"Pakistan\",\"player_type\":\"bowler\",\"player_captain\":null,\"player_cost\":0,\"player_image\":\"1455112905987-player.png\",\"player_seo_title\":\"Aizaz Cheema\",\"player_seo_keyword\":null,\"player_url\":\"aizaz-cheema\",\"player_visibility\":\"true\",\"player_keeper\":null,\"player_seo_description\":null,\"player_description\":\"\"},\"Thisara Perera\":{\"id\":\"52C470D6-E0CE-434C-896C-81F204B5A3F9\",\"player_name\":\"Thisara Perera\",\"player_country\":\"Sri Lanka\",\"player_type\":\"alrounder\",\"player_captain\":null,\"player_cost\":400000,\"player_image\":\"1453875951805-player.jpeg\",\"player_seo_title\":\"Thisara Perera\",\"player_seo_keyword\":null,\"player_url\":\"thisara-perera\",\"player_visibility\":\"true\",\"player_keeper\":null,\"player_seo_description\":null,\"player_description\":\"\"},\"Jade Dernbach\":{\"id\":\"3D068555-1234-4E38-B8C6-96FD1744C363\",\"player_name\":\"Jade Dernbach\",\"player_country\":\"England\",\"player_type\":\"bowler\",\"player_captain\":null,\"player_cost\":300000,\"player_image\":\"1453875933239-player.jpeg\",\"player_seo_title\":\"Jade Dernbach\",\"player_seo_keyword\":null,\"player_url\":\"jade-dernbach\",\"player_visibility\":\"true\",\"player_keeper\":null,\"player_seo_description\":null,\"player_description\":\"\"},\"Kevin Pietersen\":{\"id\":\"8FC7A4C9-FE14-4C53-9510-B4ED8C2B465E\",\"player_name\":\"Kevin Pietersen\",\"player_country\":\"England\",\"player_type\":\"batsman\",\"player_captain\":null,\"player_cost\":500000,\"player_image\":\"1455111785108-player.png\",\"player_seo_title\":\"Kevin Pietersen\",\"player_seo_keyword\":null,\"player_url\":\"kevin-pietersen\",\"player_visibility\":\"true\",\"player_keeper\":null,\"player_seo_description\":null,\"player_description\":\"\"},\"Grant Elliot\":{\"id\":\"9CAE63EF-59A7-46F4-B75B-4DBCAB39D7DD\",\"player_name\":\"Grant Elliot\",\"player_country\":\"New Zealand\",\"player_type\":\"alrounder\",\"player_captain\":null,\"player_cost\":300000,\"player_image\":\"1455206450743-player.jpeg\",\"player_seo_title\":\"Grant Elliot\",\"player_seo_keyword\":null,\"player_url\":\"grant-elliot\",\"player_visibility\":\"true\",\"player_keeper\":null,\"player_seo_description\":null,\"player_description\":\"\"},\"K Sangakkara\":{\"id\":\"8A7D4508-524B-42DA-9794-F842A686FF2B\",\"player_name\":\"K Sangakkara\",\"player_country\":\"Sri Lanka\",\"player_type\":\"wicket keeper\",\"player_captain\":null,\"player_cost\":0,\"player_image\":\"\",\"player_seo_title\":\"K Sangakkara\",\"player_seo_keyword\":null,\"player_url\":\"k-sangakkara\",\"player_visibility\":\"true\",\"player_keeper\":null,\"player_seo_description\":null,\"player_description\":\"\"},\"Nathan McCullum\":{\"id\":\"08694AD9-96E7-4CE3-9414-7FAB91FF1ADC\",\"player_name\":\"Nathan McCullum\",\"player_country\":\"New Zealand\",\"player_type\":\"alrounder\",\"player_captain\":null,\"player_cost\":400000,\"player_image\":\"1455879102412-player.jpeg\",\"player_seo_title\":\"Nathan McCullum\",\"player_seo_keyword\":null,\"player_url\":\"nathan-mccullum\",\"player_visibility\":\"true\",\"player_keeper\":null,\"player_seo_description\":null,\"player_description\":\"\"}}","teamPlayersorting":null,"team_description":"","win":6,"points":0,"declare":0,"lost":2,"runrate":null,"played":8,"team_nrr":"+0.216","sort_index":"2"},{"id":"6CAF4B50-0209-4639-951D-C67E624CC64A","__createdAt":"2016-01-01T06:41:02.254Z","__updatedAt":"2016-02-18T18:13:10.738Z","__version":{"0":0,"1":0,"2":0,"3":0,"4":0,"5":13,"6":47,"7":126,"length":8},"__deleted":false,"team_image":"1453111086101-team.png","team_name":"Islamabad United","team_players_Select":null,"team_seo_title":"Islamabad United","team_seo_keyword":null,"team_url":"islamabad-united","team_visibility":"true","team_seo_description":"United We Win","teamPlayers":null,"team_players_name":"{\"Amad Butt\":{\"id\":\"72B1E3D6-178D-41CD-9772-AF1ABC976624\",\"player_name\":\"Amad Butt\",\"player_country\":\"Pakistan\",\"player_type\":\"alrounder\",\"player_captain\":null,\"player_cost\":100000,\"player_image\":\"1453267515945-player.gif\",\"player_seo_title\":\"Ammad Butt\",\"player_seo_keyword\":null,\"player_url\":\"ammad-butt\",\"player_visibility\":\"true\",\"player_keeper\":null,\"player_seo_description\":null,\"player_description\":\"\"},\"Andre Russell\":{\"id\":\"B6B15FDA-BF12-4417-BBD1-7346FC950CA3\",\"player_name\":\"Andre Russell\",\"player_country\":\"West Indies\",\"player_type\":\"alrounder\",\"player_captain\":null,\"player_cost\":500000,\"player_image\":\"1455114612035-player.png\",\"player_seo_title\":\"Andre Russell\",\"player_seo_keyword\":null,\"player_url\":\"andre-russell\",\"player_visibility\":\"true\",\"player_keeper\":null,\"player_seo_description\":null,\"player_description\":\"\"},\"Sharjeel Khan\":{\"id\":\"72FD67A7-6719-41FD-9023-CB95B3D3EE01\",\"player_name\":\"Sharjeel Khan\",\"player_country\":\"Pakistan\",\"player_type\":\"batsman\",\"player_captain\":null,\"player_cost\":300000,\"player_image\":\"1455114424769-player.png\",\"player_seo_title\":\"Sharjeel Khan\",\"player_seo_keyword\":null,\"player_url\":\"sharjeel-khan\",\"player_visibility\":\"true\",\"player_keeper\":null,\"player_seo_description\":null,\"player_description\":\"\"},\"Ashar Zaidi\":{\"id\":\"2BB83C33-5B44-4518-AD53-D330CFA4E68A\",\"player_name\":\"Ashar Zaidi\",\"player_country\":\"Pakistan\",\"player_type\":\"alrounder\",\"player_captain\":null,\"player_cost\":0,\"player_image\":\"1455114130031-player.png\",\"player_seo_title\":\"Ashar Zaidi\",\"player_seo_keyword\":null,\"player_url\":\"ashar-zaidi\",\"player_visibility\":\"true\",\"player_keeper\":null,\"player_seo_description\":null,\"player_description\":\"\"},\"Saeed Ajmal\":{\"id\":\"73BF9260-C429-489A-B0D9-C13EDCAA6834\",\"player_name\":\"Saeed Ajmal\",\"player_country\":\"Pakistan\",\"player_type\":\"bowler\",\"player_captain\":null,\"player_cost\":0,\"player_image\":\"1455114094242-player.png\",\"player_seo_title\":\"Saeed Ajmal\",\"player_seo_keyword\":null,\"player_url\":\"saeed-ajmal\",\"player_visibility\":\"true\",\"player_keeper\":null,\"player_seo_description\":null,\"player_description\":\"\"},\"Shane Watson\":{\"id\":\"1974DD87-1FDB-40BC-AB9F-A9A0C78F46A1\",\"player_name\":\"Shane Watson\",\"player_country\":\"Australia\",\"player_type\":\"alrounder\",\"player_captain\":null,\"player_cost\":500000,\"player_image\":\"1455114590553-player.png\",\"player_seo_title\":\"Shane Watson\",\"player_seo_keyword\":null,\"player_url\":\"shane-watson\",\"player_visibility\":\"true\",\"player_keeper\":null,\"player_seo_description\":null,\"player_description\":\"\"},\"Samuel Badree\":{\"id\":\"8E09137B-C693-42EB-A2D2-26E9A69CA43A\",\"player_name\":\"Samuel Badree\",\"player_country\":\"West Indies\",\"player_type\":\"bowler\",\"player_captain\":null,\"player_cost\":400000,\"player_image\":\"1455114483973-player.png\",\"player_seo_title\":\"Samuel Badree\",\"player_seo_keyword\":null,\"player_url\":\"samuel-badree\",\"player_visibility\":\"true\",\"player_keeper\":null,\"player_seo_description\":null,\"player_description\":\"\"},\"Babar Azam\":{\"id\":\"31132285-7357-4975-9C84-D5B581C135A3\",\"player_name\":\"Babar Azam\",\"player_country\":\"Pakistan\",\"player_type\":\"batsman\",\"player_captain\":null,\"player_cost\":200000,\"player_image\":\"1455114331570-player.png\",\"player_seo_title\":\"Babar Azam\",\"player_seo_keyword\":null,\"player_url\":\"babar-azam\",\"player_visibility\":\"true\",\"player_keeper\":null,\"player_seo_description\":null,\"player_description\":\"\"},\"Brad Haddin\":{\"id\":\"65A66DE0-2C73-4179-BA05-8C0EBEEA209B\",\"player_name\":\"Brad Haddin\",\"player_country\":\"Australia\",\"player_type\":\"wicket keeper\",\"player_captain\":null,\"player_cost\":400000,\"player_image\":\"1455114541435-player.png\",\"player_seo_title\":\"Brad Haddin\",\"player_seo_keyword\":null,\"player_url\":\"brad-haddin\",\"player_visibility\":\"true\",\"player_keeper\":true,\"player_seo_description\":null,\"player_description\":\"\"},\"Misbah ul Haq\":{\"id\":\"1E5A7E75-5DD7-4FD1-8FE3-AD3F29B64C5C\",\"player_name\":\"Misbah ul Haq\",\"player_country\":\"Pakistan\",\"player_type\":\"batsman\",\"player_captain\":\"Misbah ul Haq\",\"player_cost\":500000,\"player_image\":\"1455114654371-player.png\",\"player_seo_title\":\"Misbah ul Haq\",\"player_seo_keyword\":null,\"player_url\":\"misbah-ul-haq\",\"player_visibility\":\"true\",\"player_keeper\":null,\"player_seo_description\":null,\"player_description\":\"\"},\"Mohammad Sami\":{\"id\":\"0A4C75BA-E378-42DB-B52A-65BA32C6905E\",\"player_name\":\"Mohammad Sami\",\"player_country\":\"Pakistan\",\"player_type\":\"bowler\",\"player_captain\":null,\"player_cost\":300000,\"player_image\":\"1455114462292-player.png\",\"player_seo_title\":\"Mohammad Sami\",\"player_seo_keyword\":null,\"player_url\":\"mohammad-sami\",\"player_visibility\":\"true\",\"player_keeper\":null,\"player_seo_description\":null,\"player_description\":\"\"},\"Umar Amin\":{\"id\":\"0A17D7DD-FC6D-4682-AE38-BF75AA093EE4\",\"player_name\":\"Umar Amin\",\"player_country\":\"Pakistan\",\"player_type\":\"alrounder\",\"player_captain\":null,\"player_cost\":200000,\"player_image\":\"1455114309633-player.png\",\"player_seo_title\":\"Umar Amin\",\"player_seo_keyword\":null,\"player_url\":\"umar-amin\",\"player_visibility\":\"true\",\"player_keeper\":null,\"player_seo_description\":null,\"player_description\":\"\"},\"Kamran Ghulam\":{\"id\":\"F9352530-8466-4DBA-A776-FDAA918D04D8\",\"player_name\":\"Kamran Ghulam\",\"player_country\":\"Pakistan\",\"player_type\":\"alrounder\",\"player_captain\":null,\"player_cost\":200000,\"player_image\":\"1455114248009-player.png\",\"player_seo_title\":\"Kamran Ghulam\",\"player_seo_keyword\":null,\"player_url\":\"kamran-ghulam\",\"player_visibility\":\"true\",\"player_keeper\":null,\"player_seo_description\":null,\"player_description\":\"\"},\"Imran Khalid\":{\"id\":\"8C5964B2-195E-415C-BB14-74A6B9AFE208\",\"player_name\":\"Imran Khalid\",\"player_country\":\"Pakistan\",\"player_type\":\"alrounder\",\"player_captain\":null,\"player_cost\":200000,\"player_image\":\"1455114276725-player.png\",\"player_seo_title\":\"Imran Khalid\",\"player_seo_keyword\":null,\"player_url\":\"imran-khalid\",\"player_visibility\":\"true\",\"player_keeper\":null,\"player_seo_description\":null,\"player_description\":\"\"},\"Ruman Raees\":{\"id\":\"84BB78EB-7BA4-4DA9-84CE-89008D0C47B6\",\"player_name\":\"Ruman Raees\",\"player_country\":\"Pakistan\",\"player_type\":\"bowler\",\"player_captain\":null,\"player_cost\":100000,\"player_image\":\"1455114204994-player.png\",\"player_seo_title\":\"Rumman Raees\",\"player_seo_keyword\":null,\"player_url\":\"rumman-raees\",\"player_visibility\":\"true\",\"player_keeper\":null,\"player_seo_description\":null,\"player_description\":\"\"},\"Mohammad Irfan\":{\"id\":\"69F5A8D2-2679-402D-90F8-65C2F73B8BE3\",\"player_name\":\"Mohammad Irfan\",\"player_country\":\"Pakistan\",\"player_type\":\"bowler\",\"player_captain\":null,\"player_cost\":400000,\"player_image\":\"1455114516361-player.png\",\"player_seo_title\":\"Mohammad Irfan\",\"player_seo_keyword\":null,\"player_url\":\"mohammad-irfan\",\"player_visibility\":\"true\",\"player_keeper\":null,\"player_seo_description\":null,\"player_description\":\"\"},\"Sam Billings\":{\"id\":\"1ACE2EA8-843E-4AE2-833B-8EF78DDE432A\",\"player_name\":\"Sam Billings\",\"player_country\":\"England\",\"player_type\":\"wicket keeper\",\"player_captain\":null,\"player_cost\":200000,\"player_image\":\"1455114228282-player.png\",\"player_seo_title\":\"Sam Billings\",\"player_seo_keyword\":null,\"player_url\":\"sam-billings\",\"player_visibility\":\"true\",\"player_keeper\":true,\"player_seo_description\":null,\"player_description\":\"\"},\"Khalid Latif\":{\"id\":\"F3D0DB74-6FA9-464C-86C1-7D51E2C24E2B\",\"player_name\":\"Khalid Latif\",\"player_country\":\"Pakistan\",\"player_type\":\"batsman\",\"player_captain\":null,\"player_cost\":300000,\"player_image\":\"1453267189018-player.gif\",\"player_seo_title\":\"Khalid Latif\",\"player_seo_keyword\":null,\"player_url\":\"khalid-latif\",\"player_visibility\":\"true\",\"player_keeper\":null,\"player_seo_description\":null,\"player_description\":\"\"},\"Umar Siddiq\":{\"id\":\"AAF0EB79-994D-4E4A-8F94-AC4C48F351E9\",\"player_name\":\"Umar Siddiq\",\"player_country\":\"Pakistan\",\"player_type\":\"batsman\",\"player_captain\":null,\"player_cost\":0,\"player_image\":\"1453267333049-player.gif\",\"player_seo_title\":\"Umar Siddiq\",\"player_seo_keyword\":null,\"player_url\":\"umar-siddiq\",\"player_visibility\":\"true\",\"player_keeper\":null,\"player_seo_description\":null,\"player_description\":\"\"},\"Hussain Talat\":{\"id\":\"3637C66A-AA48-48A8-A591-31B9C2C34C71\",\"player_name\":\"Hussain Talat\",\"player_country\":\"Pakistan\",\"player_type\":\"alrounder\",\"player_captain\":null,\"player_cost\":0,\"player_image\":\"1453267413537-player.gif\",\"player_seo_title\":\"Hussain Talat\",\"player_seo_keyword\":null,\"player_url\":\"hussain-talat\",\"player_visibility\":\"true\",\"player_keeper\":null,\"player_seo_description\":null,\"player_description\":\"\"},\"Asif Ali\":{\"id\":\"578D61D3-7F5D-4A90-BB67-9CD5CBF635B4\",\"player_name\":\"Asif Ali\",\"player_country\":\"Pakistan\",\"player_type\":\"batsman\",\"player_captain\":null,\"player_cost\":0,\"player_image\":\"\",\"player_seo_title\":\"Asif Ali\",\"player_seo_keyword\":null,\"player_url\":\"asif-ali\",\"player_visibility\":\"true\",\"player_keeper\":null,\"player_seo_description\":null,\"player_description\":\"\"},\"Azhar Mahmood\":{\"id\":\"8A773281-EFBA-48CB-9F40-D1191E323616\",\"player_name\":\"Azhar Mahmood\",\"player_country\":\"England\",\"player_type\":\"alrounder\",\"player_captain\":null,\"player_cost\":0,\"player_image\":\"\",\"player_seo_title\":\"Azhar Mahmood\",\"player_seo_keyword\":null,\"player_url\":\"azhar-mahmood\",\"player_visibility\":\"true\",\"player_keeper\":null,\"player_seo_description\":null,\"player_description\":\"\"},\"Dwayne Smith\":{\"id\":\"8AA53793-E90D-466E-AF5D-AF9B56E9A353\",\"player_name\":\"Dwayne Smith\",\"player_country\":\"West Indies\",\"player_type\":\"alrounder\",\"player_captain\":null,\"player_cost\":0,\"player_image\":\"\",\"player_seo_title\":\"Dwayne Smith\",\"player_seo_keyword\":null,\"player_url\":\"dwayne-smith\",\"player_visibility\":\"true\",\"player_keeper\":null,\"player_seo_description\":null,\"player_description\":\"\"}}","teamPlayersorting":null,"team_description":"","win":4,"points":0,"declare":0,"lost":4,"runrate":null,"played":8,"team_nrr":"-0.282","sort_index":"3"}]}